twopic/__init__.py
twopic/model.py
twopic/process.py
twopic-0.1.2.dist-info/WHEEL
twopic-0.1.2.dist-info/METADATA
twopic-0.1.2.dist-info/RECORD
