Metadata-Version: 2.1
Name: twopic
Version: 0.1.2
Summary: 
Author: Kydlaw
Author-email: kydlawj@pm.me
Requires-Python: >=3.8,<4.0
Classifier: Programming Language :: Python :: 3
Classifier: Programming Language :: Python :: 3.8
Requires-Dist: bokeh (>=2.2.1,<3.0.0)
Requires-Dist: matplotlib (>=3.3.2,<4.0.0)
Requires-Dist: nltk (>=3.5,<4.0)
Requires-Dist: pandas (>=1.1.2,<2.0.0)
Requires-Dist: tensorflow (>=2.3.1,<3.0.0)
Requires-Dist: tensorflow_hub (>=0.9.0,<0.10.0)
Requires-Dist: tqdm (>=4.50.0,<5.0.0)
Requires-Dist: twittenizer (>=0.0.5,<0.0.6)
